{"py/object": "diary.Diary", "dates": [1, 2, 3, 4, 5, 6, 7, 8, 9, 10], "attendances": {"Janusz Golonka": {"python": {"10": false, "1": true, "3": false, "2": true, "5": true, "4": true, "7": true, "6": true, "9": true, "8": false}, "radio": {"10": false, "1": false, "3": true, "2": true, "5": false, "4": true, "7": false, "6": true, "9": false, "8": true}, "circuit theory": {"10": true, "1": true, "3": false, "2": true, "5": false, "4": true, "7": false, "6": true, "9": true, "8": false}, "physics": {"10": false, "1": false, "3": true, "2": true, "5": false, "4": true, "7": false, "6": false, "9": false, "8": false}, "algebra": {"10": false, "1": true, "3": false, "2": true, "5": true, "4": false, "7": true, "6": false, "9": true, "8": true}}, "Henryk Janowski": {"python": {"10": false, "1": false, "3": true, "2": false, "5": false, "4": false, "7": false, "6": true, "9": false, "8": true}, "radio": {"10": true, "1": true, "3": false, "2": false, "5": true, "4": false, "7": true, "6": true, "9": true, "8": true}, "circuit theory": {"10": false, "1": true, "3": true, "2": false, "5": true, "4": true, "7": false, "6": false, "9": true, "8": true}, "physics": {"10": false, "1": false, "3": true, "2": true, "5": false, "4": false, "7": true, "6": true, "9": false, "8": false}, "algebra": {"10": false, "1": true, "3": true, "2": false, "5": true, "4": false, "7": false, "6": false, "9": true, "8": false}}, "Adam Nowak": {"python": {"10": false, "1": true, "3": false, "2": false, "5": false, "4": true, "7": true, "6": false, "9": false, "8": false}, "radio": {"10": true, "1": true, "3": true, "2": false, "5": false, "4": false, "7": true, "6": false, "9": false, "8": true}, "circuit theory": {"10": true, "1": false, "3": true, "2": false, "5": false, "4": true, "7": false, "6": true, "9": false, "8": false}, "physics": {"10": false, "1": false, "3": true, "2": true, "5": false, "4": false, "7": false, "6": false, "9": false, "8": false}, "algebra": {"10": true, "1": false, "3": false, "2": true, "5": true, "4": true, "7": false, "6": true, "9": false, "8": false}}}, "students": ["Adam Nowak", "Janusz Golonka", "Henryk Janowski"], "classes": ["python", "algebra", "circuit theory", "physics", "radio"], "scores": {"Janusz Golonka": {"python": 2.0, "radio": 2.0, "circuit theory": 2.0, "physics": 2.0, "algebra": 4.0}, "Henryk Janowski": {"python": 4.0, "radio": 2.0, "circuit theory": 4.5, "physics": 5.0, "algebra": 5.0}, "Adam Nowak": {"python": 4.0, "radio": 2.0, "circuit theory": 3.0, "physics": 5.0, "algebra": 3.0}}}